Workbook

Sheet Legend
A1: RFI Response Comparison — PRJ-STEEL-ROLLING-LINE-01 (template v1, 2026-09-23)
A2: INTERNAL ONLY. Do not send to vendors.
A4: How to use
A5: 1. One sheet per item (Furnace, DC Motor, Stand, Gearbox). One column per vendor response (D:G).
A6: 2. Type only in yellow cells with blue text. Black cells are formulas — do not overwrite them.
A7: 3. Column C 'Our basis' comes from the v5 RFIs / ENGINEERING_PACKAGE_A. Numeric checks compare each response to it.
A8: 4. 'Price type' must use the procurement evidence taxonomy. Only FORMAL QUOTE counts toward budget ('Counts for budget?').
A9: 5. Enter the FX rate to USD you actually use and its date in the Summary sheet; every USD figure recalculates.
A10: 6. 'Scope gap allowance' = your estimate (USD) of items the vendor marked OUT that we still need. Keep it explicit, never hidden.
A11: 7. Column D on each sheet holds an EXAMPLE row set (italic) showing the expected format. Clear it before real use.
A13: Evidence / price-type tags
A14: FACT · SELLER CLAIM · TRANSACTION PRICE · AUCTION START PRICE · ADVERTISED PRICE · FORMAL QUOTE · ESTIMATE · ASSUMPTION · UNKNOWN
... A17: No response is formal RFQ pricing until Gate B (grade, reversing/one-way, pass schedule, acceptance criteria) is closed. No order before Gate C (hold points 1–7, qualified-engineer sign-off).

Sheet Furnace
A1: Field | B1: Unit | C1: Our basis / requirement | D1: Vendor A (example) | E1: Vendor B | F1: Vendor C | G1: Vendor D
A2: Identity (Gate A)
A3: Registered legal name (Chinese) | C3: must match business licence | D3: 南京某某炉业有限公司
A4: Unified social credit code | C4: 18 characters | D4: 91320100XXXXXXXXXX
A5: Checked on gsxt.gov.cn by a person? | B5: Yes/No/Unknown | C5: Yes required | D5: No
A6: Manufacturer or trader? | C6: manufacturer preferred | D6: Manufacturer
A7: Commercial
A8: Price type | B8: tag | C8: FORMAL QUOTE to count | D8: ADVERTISED PRICE
A9: Price (as quoted) | B9: currency units | D9: 1000000
A10: Currency | B10: code | D10: CNY
A11: FX to USD (from Summary) | B11: USD per unit | D11: =IFERROR(IF(INDEX(Summary!$C$6:$C$12,MATCH(D10,Summary!$B$6:$B$12,0))=0,"set FX",INDEX(Summary!$C$6:$C$12,MATCH(D10,Summary!$B$6:$B$12,0))),IF(D10="","","set FX")) -> set FX | E11: =IFERROR(IF(INDEX(Summary!$C$6:$C$12,MATCH(E10,Summary!$B$6:$B$12,0))=0,"set FX",INDEX(Summary!$C$6:$C$12,MATCH(E10,Summary!$B$6:$B$12,0))),IF(E10="","","set FX")) | F11: =IFERROR(IF(INDEX(Summary!$C$6:$C$12,MATCH(F10,Summary!$B$6:$B$12,0))=0,"set FX",INDEX(Summary!$C$6:$C$12,MATCH(F10,Summary!$B$6:$B$12,0))),IF(F10="","","set FX")) | G11: =IFERROR(IF(INDEX(Summary!$C$6:$C$12,MATCH(G10,Summary!$B$6:$B$12,0))=0,"set FX",INDEX(Summary!$C$6:$C$12,MATCH(G10,Summary!$B$6:$B$12,0))),IF(G10="","","set FX"))
A12: Price in USD | B12: USD | D12: =IF(OR(D9="",NOT(ISNUMBER(D11))),"",D9*D11) | E12: =IF(OR(E9="",NOT(ISNUMBER(E11))),"",E9*E11) | F12: =IF(OR(F9="",NOT(ISNUMBER(F11))),"",F9*F11) | G12: =IF(OR(G9="",NOT(ISNUMBER(G11))),"",G9*G11)
A13: Incoterm + named place | C13: CIF destination port basis for comparison | D13: FOB Shanghai
A14: Freight + insurance to reach CIF basis | B14: USD | C14: your estimate; 0 if already CIF | D14: 60000
A15: Tax included? | B15: Yes/No | C15: state explicitly | D15: No
A16: Scope gap allowance | B16: USD | C16: items marked OUT that we still need | D16: 25000
A17: Normalised comparable price (CIF + gaps) | B17: USD | D17: =IF(D12="","",D12+N(D14)+N(D16)) | E17: =IF(E12="","",E12+N(E14)+N(E16)) | F17: =IF(F12="","",F12+N(F14)+N(F16)) | G17: =IF(G12="","",G12+N(G14)+N(G16))
A18: Counts for budget? | C18: only FORMAL QUOTE | D18: =IF(D8="","",IF(D8="FORMAL QUOTE","YES","NO — not budget-grade")) -> NO — not budget-grade | E18: =IF(E8="","",IF(E8="FORMAL QUOTE","YES","NO — not budget-grade")) | F18: =IF(F8="","",IF(F8="FORMAL QUOTE","YES","NO — not budget-grade")) | G18: =IF(G8="","",IF(G8="FORMAL QUOTE","YES","NO — not budget-grade"))
A19: Delivery time from order | B19: weeks | D19: 40
A20: Payment terms | D20: 30% advance / 70% against B/L
A21: Validity of offer | B21: days | D21: 30
A22: Reference installations (customer, country, year) | C22: similar scope | D22: —
A23: Technical — against our basis
A24: Capacity for 400×125×3000 slab, cold charge | B24: t/h | C24: ≥ 20 (FACT basis) | D24: 22
A25: Inner width | B25: mm | C25: > 3000 for crosswise charging | D25: 3400
A26: Charging orientation | C26: crosswise expected | D26: crosswise
A27: Specific hearth loading | B27: kg/(m²·h) | C27: state basis | D27: 400
A28: Discharge temperature | B28: °C | C28: 1250 target (CLAIM) | D28: 1250
A29: Specific energy, cold charge | B29: GJ/t | C29: lower is better | D29: 1.3
A30: Scale loss guarantee | B30: % | C30: lower is better | D30: 1
A31: NOx guarantee | B31: mg/Nm³ | D31: 200
A32: New or used | C32: both acceptable | D32: New
A34: Automatic checks (formulas)
A35: CHECK: Capacity for 400×125×3000 slab, cold charge >= 20 | C35: limit 20 | D35: =IF(D24="","",IF(ISNUMBER(D24),IF(D24>=20,"PASS","FAIL"),"non-numeric")) -> PASS | E35: =IF(E24="","",IF(ISNUMBER(E24),IF(E24>=20,"PASS","FAIL"),"non-numeric")) | F35: =IF(F24="","",IF(ISNUMBER(F24),IF(F24>=20,"PASS","FAIL"),"non-numeric")) | G35: =IF(G24="","",IF(ISNUMBER(G24),IF(G24>=20,"PASS","FAIL"),"non-numeric"))
A36: CHECK: Inner width > 3000 | C36: limit 3000 | D36: =IF(D25="","",IF(ISNUMBER(D25),IF(D25>3000,"PASS","FAIL"),"non-numeric")) -> PASS | E36: =IF(E25="","",IF(ISNUMBER(E25),IF(E25>3000,"PASS","FAIL"),"non-numeric")) | F36: =IF(F25="","",IF(ISNUMBER(F25),IF(F25>3000,"PASS","FAIL"),"non-numeric")) | G36: =IF(G25="","",IF(ISNUMBER(G25),IF(G25>3000,"PASS","FAIL"),"non-numeric"))
A37: Checks passed | D37: =COUNTIF(D35:D36,"PASS")&" / "&COUNTA(D35:D36)-COUNTBLANK(D35:D36) -> 2 / 2 | E37: =COUNTIF(E35:E36,"PASS")&" / "&COUNTA(E35:E36)-COUNTBLANK(E35:E36) -> 0 / 0 | F37: =COUNTIF(F35:F36,"PASS")&" / "&COUNTA(F35:F36)-COUNTBLANK(F35:F36) -> 0 / 0 | G37: =COUNTIF(G35:G36,"PASS")&" / "&COUNTA(G35:G36)-COUNTBLANK(G35:G36) -> 0 / 0

Sheet DC Motor
A1: Field | B1: Unit | C1: Our basis / requirement | D1: Vendor A (example) | E1: Vendor B | F1: Vendor C | G1: Vendor D
A2: Identity (Gate A)
A3: Registered legal name (Chinese) | C3: must match business licence | D3: 南京某某炉业有限公司
A4: Unified social credit code | C4: 18 characters | D4: 91320100XXXXXXXXXX
A5: Checked on gsxt.gov.cn by a person? | B5: Yes/No/Unknown | C5: Yes required | D5: No
A6: Manufacturer or trader? | C6: manufacturer preferred | D6: Manufacturer
A7: Commercial
A8: Price type | B8: tag | C8: FORMAL QUOTE to count | D8: ADVERTISED PRICE
A9: Price (as quoted) | B9: currency units | D9: 1000000
A10: Currency | B10: code | D10: CNY
A11: FX to USD (from Summary) | B11: USD per unit | D11: =IFERROR(IF(INDEX(Summary!$C$6:$C$12,MATCH(D10,Summary!$B$6:$B$12,0))=0,"set FX",INDEX(Summary!$C$6:$C$12,MATCH(D10,Summary!$B$6:$B$12,0))),IF(D10="","","set FX")) -> set FX | E11: =IFERROR(IF(INDEX(Summary!$C$6:$C$12,MATCH(E10,Summary!$B$6:$B$12,0))=0,"set FX",INDEX(Summary!$C$6:$C$12,MATCH(E10,Summary!$B$6:$B$12,0))),IF(E10="","","set FX")) | F11: =IFERROR(IF(INDEX(Summary!$C$6:$C$12,MATCH(F10,Summary!$B$6:$B$12,0))=0,"set FX",INDEX(Summary!$C$6:$C$12,MATCH(F10,Summary!$B$6:$B$12,0))),IF(F10="","","set FX")) | G11: =IFERROR(IF(INDEX(Summary!$C$6:$C$12,MATCH(G10,Summary!$B$6:$B$12,0))=0,"set FX",INDEX(Summary!$C$6:$C$12,MATCH(G10,Summary!$B$6:$B$12,0))),IF(G10="","","set FX"))
A12: Price in USD | B12: USD | D12: =IF(OR(D9="",NOT(ISNUMBER(D11))),"",D9*D11) | E12: =IF(OR(E9="",NOT(ISNUMBER(E11))),"",E9*E11) | F12: =IF(OR(F9="",NOT(ISNUMBER(F11))),"",F9*F11) | G12: =IF(OR(G9="",NOT(ISNUMBER(G11))),"",G9*G11)
A13: Incoterm + named place | C13: CIF destination port basis for comparison | D13: FOB Shanghai
A14: Freight + insurance to reach CIF basis | B14: USD | C14: your estimate; 0 if already CIF | D14: 60000
A15: Tax included? | B15: Yes/No | C15: state explicitly | D15: No
A16: Scope gap allowance | B16: USD | C16: items marked OUT that we still need | D16: 25000
A17: Normalised comparable price (CIF + gaps) | B17: USD | D17: =IF(D12="","",D12+N(D14)+N(D16)) | E17: =IF(E12="","",E12+N(E14)+N(E16)) | F17: =IF(F12="","",F12+N(F14)+N(F16)) | G17: =IF(G12="","",G12+N(G14)+N(G16))
A18: Counts for budget? | C18: only FORMAL QUOTE | D18: =IF(D8="","",IF(D8="FORMAL QUOTE","YES","NO — not budget-grade")) -> NO — not budget-grade | E18: =IF(E8="","",IF(E8="FORMAL QUOTE","YES","NO — not budget-grade")) | F18: =IF(F8="","",IF(F8="FORMAL QUOTE","YES","NO — not budget-grade")) | G18: =IF(G8="","",IF(G8="FORMAL QUOTE","YES","NO — not budget-grade"))
A19: Delivery time from order | B19: weeks | D19: 40
A20: Payment terms | D20: 30% advance / 70% against B/L
A21: Validity of offer | B21: days | D21: 30
A22: Reference installations (customer, country, year) | C22: similar scope | D22: —
A23: Technical — against our basis
A24: Rating offered | B24: kW | C24: 1600 and 2000 both requested | D24: 2000
A25: Base speed | B25: rpm | C25: 300–400 (350 preferred) | D25: 350
A26: Maximum speed | B26: rpm | C26: ≈700 | D26: 700
A27: Continuous-rating basis (ambient / altitude / duty) | C27: must be stated | D27: 40 °C / 1000 m / S1
A28: Overload at base speed | B28: × for s | C28: ≥1.5× for ≥30 s | D28: 1.5
A29: Commutation-limited overload at ≈650 rpm | B29: × | C29: curve required; basis needs ≥1.02× (2000 kW) or ≥1.28× (1600 kW) for 2.9 s | D29: 1.66
A30: Rated reversals per hour | B30: 1/h | C30: ≥170 | D30: 200
A31: GD² | B31: kg·m² | C31: required (Hold Point 7) | D31: 1800
A32: Motor / converter / transformer / reactor priced separately? | B32: Yes/No | C32: Yes | D32: Yes
A34: Automatic checks (formulas)
A35: CHECK: Overload at base speed >= 1.5 | C35: limit 1.5 | D35: =IF(D28="","",IF(ISNUMBER(D28),IF(D28>=1.5,"PASS","FAIL"),"non-numeric")) -> PASS | E35: =IF(E28="","",IF(ISNUMBER(E28),IF(E28>=1.5,"PASS","FAIL"),"non-numeric")) | F35: =IF(F28="","",IF(ISNUMBER(F28),IF(F28>=1.5,"PASS","FAIL"),"non-numeric")) | G35: =IF(G28="","",IF(ISNUMBER(G28),IF(G28>=1.5,"PASS","FAIL"),"non-numeric"))
A36: CHECK: Rated reversals per hour >= 170 | C36: limit 170 | D36: =IF(D30="","",IF(ISNUMBER(D30),IF(D30>=170,"PASS","FAIL"),"non-numeric")) -> PASS | E36: =IF(E30="","",IF(ISNUMBER(E30),IF(E30>=170,"PASS","FAIL"),"non-numeric")) | F36: =IF(F30="","",IF(ISNUMBER(F30),IF(F30>=170,"PASS","FAIL"),"non-numeric")) | G36: =IF(G30="","",IF(ISNUMBER(G30),IF(G30>=170,"PASS","FAIL"),"non-numeric"))
A37: Checks passed | D37: =COUNTIF(D35:D36,"PASS")&" / "&COUNTA(D35:D36)-COUNTBLANK(D35:D36) -> 2 / 2 | E37: =COUNTIF(E35:E36,"PASS")&" / "&COUNTA(E35:E36)-COUNTBLANK(E35:E36) -> 0 / 0 | F37: =COUNTIF(F35:F36,"PASS")&" / "&COUNTA(F35:F36)-COUNTBLANK(F35:F36) -> 0 / 0 | G37: =COUNTIF(G35:G36,"PASS")&" / "&COUNTA(G35:G36)-COUNTBLANK(G35:G36) -> 0 / 0

Sheet Stand
A1: Field | B1: Unit | C1: Our basis / requirement | D1: Vendor A (example) | E1: Vendor B | F1: Vendor C | G1: Vendor D
A2: Identity (Gate A)
A3: Registered legal name (Chinese) | C3: must match business licence | D3: 南京某某炉业有限公司
A4: Unified social credit code | C4: 18 characters | D4: 91320100XXXXXXXXXX
A5: Checked on gsxt.gov.cn by a person? | B5: Yes/No/Unknown | C5: Yes required | D5: No
A6: Manufacturer or trader? | C6: manufacturer preferred | D6: Manufacturer
A7: Commercial
A8: Price type | B8: tag | C8: FORMAL QUOTE to count | D8: ADVERTISED PRICE
A9: Price (as quoted) | B9: currency units | D9: 1000000
A10: Currency | B10: code | D10: CNY
A11: FX to USD (from Summary) | B11: USD per unit | D11: =IFERROR(IF(INDEX(Summary!$C$6:$C$12,MATCH(D10,Summary!$B$6:$B$12,0))=0,"set FX",INDEX(Summary!$C$6:$C$12,MATCH(D10,Summary!$B$6:$B$12,0))),IF(D10="","","set FX")) -> set FX | E11: =IFERROR(IF(INDEX(Summary!$C$6:$C$12,MATCH(E10,Summary!$B$6:$B$12,0))=0,"set FX",INDEX(Summary!$C$6:$C$12,MATCH(E10,Summary!$B$6:$B$12,0))),IF(E10="","","set FX")) | F11: =IFERROR(IF(INDEX(Summary!$C$6:$C$12,MATCH(F10,Summary!$B$6:$B$12,0))=0,"set FX",INDEX(Summary!$C$6:$C$12,MATCH(F10,Summary!$B$6:$B$12,0))),IF(F10="","","set FX")) | G11: =IFERROR(IF(INDEX(Summary!$C$6:$C$12,MATCH(G10,Summary!$B$6:$B$12,0))=0,"set FX",INDEX(Summary!$C$6:$C$12,MATCH(G10,Summary!$B$6:$B$12,0))),IF(G10="","","set FX"))
A12: Price in USD | B12: USD | D12: =IF(OR(D9="",NOT(ISNUMBER(D11))),"",D9*D11) | E12: =IF(OR(E9="",NOT(ISNUMBER(E11))),"",E9*E11) | F12: =IF(OR(F9="",NOT(ISNUMBER(F11))),"",F9*F11) | G12: =IF(OR(G9="",NOT(ISNUMBER(G11))),"",G9*G11)
A13: Incoterm + named place | C13: CIF destination port basis for comparison | D13: FOB Shanghai
A14: Freight + insurance to reach CIF basis | B14: USD | C14: your estimate; 0 if already CIF | D14: 60000
A15: Tax included? | B15: Yes/No | C15: state explicitly | D15: No
A16: Scope gap allowance | B16: USD | C16: items marked OUT that we still need | D16: 25000
A17: Normalised comparable price (CIF + gaps) | B17: USD | D17: =IF(D12="","",D12+N(D14)+N(D16)) | E17: =IF(E12="","",E12+N(E14)+N(E16)) | F17: =IF(F12="","",F12+N(F14)+N(F16)) | G17: =IF(G12="","",G12+N(G14)+N(G16))
A18: Counts for budget? | C18: only FORMAL QUOTE | D18: =IF(D8="","",IF(D8="FORMAL QUOTE","YES","NO — not budget-grade")) -> NO — not budget-grade | E18: =IF(E8="","",IF(E8="FORMAL QUOTE","YES","NO — not budget-grade")) | F18: =IF(F8="","",IF(F8="FORMAL QUOTE","YES","NO — not budget-grade")) | G18: =IF(G8="","",IF(G8="FORMAL QUOTE","YES","NO — not budget-grade"))
A19: Delivery time from order | B19: weeks | D19: 40
A20: Payment terms | D20: 30% advance / 70% against B/L
A21: Validity of offer | B21: days | D21: 30
A22: Reference installations (customer, country, year) | C22: similar scope | D22: —
A23: Technical — against our basis
A24: Roughing or finishing design | C24: must be stated | D24: roughing
A25: Rated rolling force | B25: MN | C25: ≥ 6 | D25: 6.5
A26: Work roll diameter | B26: mm | C26: 600 | D26: 600
A27: Barrel length | B27: mm | C27: 600 | D27: 600
A28: Max rolling speed | B28: m/s | C28: ≥ 3 | D28: 3
A29: Pinion stand centre distance (if in scope) | B29: mm | C29: ≈646 preliminary | D29: 646
A30: Vendor's reading of 'center 600' | C30: interpretation | D30: roll centre at new rolls
A31: Vendor's reading of '35 tons' | C31: interpretation | D31: housing weight
A32: Mill modulus | B32: kN/mm | C32: state
A34: Automatic checks (formulas)
A35: CHECK: Rated rolling force >= 6 | C35: limit 6 | D35: =IF(D25="","",IF(ISNUMBER(D25),IF(D25>=6,"PASS","FAIL"),"non-numeric")) -> PASS | E35: =IF(E25="","",IF(ISNUMBER(E25),IF(E25>=6,"PASS","FAIL"),"non-numeric")) | F35: =IF(F25="","",IF(ISNUMBER(F25),IF(F25>=6,"PASS","FAIL"),"non-numeric")) | G35: =IF(G25="","",IF(ISNUMBER(G25),IF(G25>=6,"PASS","FAIL"),"non-numeric"))
A36: CHECK: Max rolling speed >= 3 | C36: limit 3 | D36: =IF(D28="","",IF(ISNUMBER(D28),IF(D28>=3,"PASS","FAIL"),"non-numeric")) -> PASS | E36: =IF(E28="","",IF(ISNUMBER(E28),IF(E28>=3,"PASS","FAIL"),"non-numeric")) | F36: =IF(F28="","",IF(ISNUMBER(F28),IF(F28>=3,"PASS","FAIL"),"non-numeric")) | G36: =IF(G28="","",IF(ISNUMBER(G28),IF(G28>=3,"PASS","FAIL"),"non-numeric"))
A37: Checks passed | D37: =COUNTIF(D35:D36,"PASS")&" / "&COUNTA(D35:D36)-COUNTBLANK(D35:D36) -> 2 / 2 | E37: =COUNTIF(E35:E36,"PASS")&" / "&COUNTA(E35:E36)-COUNTBLANK(E35:E36) -> 0 / 0 | F37: =COUNTIF(F35:F36,"PASS")&" / "&COUNTA(F35:F36)-COUNTBLANK(F35:F36) -> 0 / 0 | G37: =COUNTIF(G35:G36,"PASS")&" / "&COUNTA(G35:G36)-COUNTBLANK(G35:G36) -> 0 / 0

Sheet Gearbox
A1: Field | B1: Unit | C1: Our basis / requirement | D1: Vendor A (example) | E1: Vendor B | F1: Vendor C | G1: Vendor D
A2: Identity (Gate A)
A3: Registered legal name (Chinese) | C3: must match business licence | D3: 南京某某炉业有限公司
A4: Unified social credit code | C4: 18 characters | D4: 91320100XXXXXXXXXX
A5: Checked on gsxt.gov.cn by a person? | B5: Yes/No/Unknown | C5: Yes required | D5: No
A6: Manufacturer or trader? | C6: manufacturer preferred | D6: Manufacturer
A7: Commercial
A8: Price type | B8: tag | C8: FORMAL QUOTE to count | D8: ADVERTISED PRICE
A9: Price (as quoted) | B9: currency units | D9: 1000000
A10: Currency | B10: code | D10: CNY
A11: FX to USD (from Summary) | B11: USD per unit | D11: =IFERROR(IF(INDEX(Summary!$C$6:$C$12,MATCH(D10,Summary!$B$6:$B$12,0))=0,"set FX",INDEX(Summary!$C$6:$C$12,MATCH(D10,Summary!$B$6:$B$12,0))),IF(D10="","","set FX")) -> set FX | E11: =IFERROR(IF(INDEX(Summary!$C$6:$C$12,MATCH(E10,Summary!$B$6:$B$12,0))=0,"set FX",INDEX(Summary!$C$6:$C$12,MATCH(E10,Summary!$B$6:$B$12,0))),IF(E10="","","set FX")) | F11: =IFERROR(IF(INDEX(Summary!$C$6:$C$12,MATCH(F10,Summary!$B$6:$B$12,0))=0,"set FX",INDEX(Summary!$C$6:$C$12,MATCH(F10,Summary!$B$6:$B$12,0))),IF(F10="","","set FX")) | G11: =IFERROR(IF(INDEX(Summary!$C$6:$C$12,MATCH(G10,Summary!$B$6:$B$12,0))=0,"set FX",INDEX(Summary!$C$6:$C$12,MATCH(G10,Summary!$B$6:$B$12,0))),IF(G10="","","set FX"))
A12: Price in USD | B12: USD | D12: =IF(OR(D9="",NOT(ISNUMBER(D11))),"",D9*D11) | E12: =IF(OR(E9="",NOT(ISNUMBER(E11))),"",E9*E11) | F12: =IF(OR(F9="",NOT(ISNUMBER(F11))),"",F9*F11) | G12: =IF(OR(G9="",NOT(ISNUMBER(G11))),"",G9*G11)
A13: Incoterm + named place | C13: CIF destination port basis for comparison | D13: FOB Shanghai
A14: Freight + insurance to reach CIF basis | B14: USD | C14: your estimate; 0 if already CIF | D14: 60000
A15: Tax included? | B15: Yes/No | C15: state explicitly | D15: No
A16: Scope gap allowance | B16: USD | C16: items marked OUT that we still need | D16: 25000
A17: Normalised comparable price (CIF + gaps) | B17: USD | D17: =IF(D12="","",D12+N(D14)+N(D16)) | E17: =IF(E12="","",E12+N(E14)+N(E16)) | F17: =IF(F12="","",F12+N(F14)+N(F16)) | G17: =IF(G12="","",G12+N(G14)+N(G16))
A18: Counts for budget? | C18: only FORMAL QUOTE | D18: =IF(D8="","",IF(D8="FORMAL QUOTE","YES","NO — not budget-grade")) -> NO — not budget-grade | E18: =IF(E8="","",IF(E8="FORMAL QUOTE","YES","NO — not budget-grade")) | F18: =IF(F8="","",IF(F8="FORMAL QUOTE","YES","NO — not budget-grade")) | G18: =IF(G8="","",IF(G8="FORMAL QUOTE","YES","NO — not budget-grade"))
A19: Delivery time from order | B19: weeks | D19: 40
A20: Payment terms | D20: 30% advance / 70% against B/L
A21: Validity of offer | B21: days | D21: 30
A22: Reference installations (customer, country, year) | C22: similar scope | D22: —
A23: Technical — against our basis
A24: Ratio option (A 25:1 / B ≈7.1 / C vendor) | C24: quote all three | D24: B
A25: Ratio | B25: i | C25: 6.3–8.0 acceptable | D25: 7.1
A26: Rated output torque | B26: kN·m | C26: ≥ 330 (405 preferred) | D26: 405
A27: Guaranteed peak output torque | B27: kN·m | C27: ≥ 655 | D27: 700
A28: Rated power | B28: kW | C28: ≥1800 / ≥2200 | D28: 2200
A29: Roll surface speed at Ø600, 700 rpm input | B29: m/s | C29: ≈3 needed | D29: 3.1
A30: Stages | C30: 1 or 2 (2 preferred) | D30: 2
A31: Rated to ISO 6336? | B31: Yes/No | C31: Yes | D31: Yes
A32: Rated reversals per hour | B32: 1/h | C32: ≥170 | D32: 200
A34: Automatic checks (formulas)
A35: CHECK: Rated output torque >= 330 | C35: limit 330 | D35: =IF(D26="","",IF(ISNUMBER(D26),IF(D26>=330,"PASS","FAIL"),"non-numeric")) -> PASS | E35: =IF(E26="","",IF(ISNUMBER(E26),IF(E26>=330,"PASS","FAIL"),"non-numeric")) | F35: =IF(F26="","",IF(ISNUMBER(F26),IF(F26>=330,"PASS","FAIL"),"non-numeric")) | G35: =IF(G26="","",IF(ISNUMBER(G26),IF(G26>=330,"PASS","FAIL"),"non-numeric"))
A36: CHECK: Guaranteed peak output torque >= 655 | C36: limit 655 | D36: =IF(D27="","",IF(ISNUMBER(D27),IF(D27>=655,"PASS","FAIL"),"non-numeric")) -> PASS | E36: =IF(E27="","",IF(ISNUMBER(E27),IF(E27>=655,"PASS","FAIL"),"non-numeric")) | F36: =IF(F27="","",IF(ISNUMBER(F27),IF(F27>=655,"PASS","FAIL"),"non-numeric")) | G36: =IF(G27="","",IF(ISNUMBER(G27),IF(G27>=655,"PASS","FAIL"),"non-numeric"))
A37: CHECK: Rated reversals per hour >= 170 | C37: limit 170 | D37: =IF(D32="","",IF(ISNUMBER(D32),IF(D32>=170,"PASS","FAIL"),"non-numeric")) -> PASS | E37: =IF(E32="","",IF(ISNUMBER(E32),IF(E32>=170,"PASS","FAIL"),"non-numeric")) | F37: =IF(F32="","",IF(ISNUMBER(F32),IF(F32>=170,"PASS","FAIL"),"non-numeric")) | G37: =IF(G32="","",IF(ISNUMBER(G32),IF(G32>=170,"PASS","FAIL"),"non-numeric"))
A38: Checks passed | D38: =COUNTIF(D35:D37,"PASS")&" / "&COUNTA(D35:D37)-COUNTBLANK(D35:D37) -> 3 / 3 | E38: =COUNTIF(E35:E37,"PASS")&" / "&COUNTA(E35:E37)-COUNTBLANK(E35:E37) -> 0 / 0 | F38: =COUNTIF(F35:F37,"PASS")&" / "&COUNTA(F35:F37)-COUNTBLANK(F35:F37) -> 0 / 0 | G38: =COUNTIF(G35:G37,"PASS")&" / "&COUNTA(G35:G37)-COUNTBLANK(G35:G37) -> 0 / 0

Sheet Summary
A1: Summary — normalised comparable price (USD) and check results
A3: FX rates (enter the rate you use, and its date/source)
B5: Currency | C5: USD per 1 unit | D5: Date / source
B6: USD | C6: 1 | D6: identity
B7: CNY
B8: EUR
B9: IRR
B10: RUB
B11: TRY
B12: AED
A15: Item | B15: Vendor A (example) | C15: Vendor B | D15: Vendor C | E15: Vendor D
A16: Furnace — normalised USD | B16: =Furnace!D17 | C16: =Furnace!E17 | D16: =Furnace!F17 | E16: =Furnace!G17
A17: Furnace — counts for budget? | B17: =Furnace!D18 -> NO — not budget-grade | C17: =Furnace!E18 | D17: =Furnace!F18 | E17: =Furnace!G18
A18: Furnace — checks passed | B18: =Furnace!D37 -> 2 / 2 | C18: =Furnace!E37 -> 0 / 0 | D18: =Furnace!F37 -> 0 / 0 | E18: =Furnace!G37 -> 0 / 0
A20: DC Motor — normalised USD | B20: ='DC Motor'!D17 | C20: ='DC Motor'!E17 | D20: ='DC Motor'!F17 | E20: ='DC Motor'!G17
A21: DC Motor — counts for budget? | B21: ='DC Motor'!D18 -> NO — not budget-grade | C21: ='DC Motor'!E18 | D21: ='DC Motor'!F18 | E21: ='DC Motor'!G18
A22: DC Motor — checks passed | B22: ='DC Motor'!D37 -> 2 / 2 | C22: ='DC Motor'!E37 -> 0 / 0 | D22: ='DC Motor'!F37 -> 0 / 0 | E22: ='DC Motor'!G37 -> 0 / 0
A24: Stand — normalised USD | B24: =Stand!D17 | C24: =Stand!E17 | D24: =Stand!F17 | E24: =Stand!G17
A25: Stand — counts for budget? | B25: =Stand!D18 -> NO — not budget-grade | C25: =Stand!E18 | D25: =Stand!F18 | E25: =Stand!G18
A26: Stand — checks passed | B26: =Stand!D37 -> 2 / 2 | C26: =Stand!E37 -> 0 / 0 | D26: =Stand!F37 -> 0 / 0 | E26: =Stand!G37 -> 0 / 0
A28: Gearbox — normalised USD | B28: =Gearbox!D17 | C28: =Gearbox!E17 | D28: =Gearbox!F17 | E28: =Gearbox!G17
A29: Gearbox — counts for budget? | B29: =Gearbox!D18 -> NO — not budget-grade | C29: =Gearbox!E18 | D29: =Gearbox!F18 | E29: =Gearbox!G18
A30: Gearbox — checks passed | B30: =Gearbox!D38 -> 3 / 3 | C30: =Gearbox!E38 -> 0 / 0 | D30: =Gearbox!F38 -> 0 / 0 | E30: =Gearbox!G38 -> 0 / 0
